code_20220301_rayeesck/__init__.py
code_20220301_rayeesck/solution.py
code_20220301_rayeesck/test.py
code_20220301_rayeesck-0.0.1.dist-info/LICENCE
code_20220301_rayeesck-0.0.1.dist-info/METADATA
code_20220301_rayeesck-0.0.1.dist-info/WHEEL
code_20220301_rayeesck-0.0.1.dist-info/top_level.txt
code_20220301_rayeesck-0.0.1.dist-info/RECORD
