Metadata-Version: 2.1
Name: code-20220301-rayeesck
Version: 0.0.1
Summary: A sample package to calculate bmi
Home-page: https://github.com/Rayeesceekey/code-20220301-rayeesck/code_20220301_rayees
Author: rayees
Author-email: xx@yy.com
License: MIT
Platform: UNKNOWN
Requires-Python: >=3.6
Requires-Dist: pandas
Requires-Dist: dask
